AutoCADlib/AutoCAD_Module.py
AutoCADlib/__init__.py
AutoCADlib/__main__.py
autocadlib-0.1.2.dist-info/licenses/LICENSE
autocadlib-0.1.2.dist-info/METADATA
autocadlib-0.1.2.dist-info/WHEEL
autocadlib-0.1.2.dist-info/entry_points.txt
autocadlib-0.1.2.dist-info/top_level.txt
autocadlib-0.1.2.dist-info/RECORD
