Metadata-Version: 2.4
Name: AutoCADlib
Version: 0.1.2
Summary: A professional AutoCAD automation package with many functions.
Home-page: https://github.com/Jones-peter
Author: Jones Peter
Author-email: jonespetersoftware@gmail.com
License: MIT
Keywords: autocad,automation,activex,comtypes,AutoCAD,AutoCADlib
Classifier: Programming Language :: Python :: 3
Classifier: License :: OSI Approved :: MIT License
Classifier: Intended Audience :: Developers
Classifier: Intended Audience :: System Administrators
Classifier: Operating System :: Microsoft :: Windows
License-File: LICENSE
Requires-Dist: pywin32
Requires-Dist: psutil
Dynamic: author
Dynamic: author-email
Dynamic: classifier
Dynamic: description
Dynamic: description-content-type
Dynamic: home-page
Dynamic: keywords
Dynamic: license
Dynamic: license-file
Dynamic: requires-dist
Dynamic: summary
